doc/source/conf.py
doc/source/tough3/figures/porosity_permeability.py
examples/co2_leakage_along_a_fault/1_generate_mesh_in_python_with_gmsh.py
examples/co2_leakage_along_a_fault/2_generate_mesh_and_incon_files.py
examples/co2_leakage_along_a_fault/3_generate_model_parameters_input_file.py
examples/co2_leakage_along_a_fault/4_import_and_visualize_simulation_outputs_in_pyvista.py
examples/heat_pipe_in_cylindrical_geometry/1_preprocessing.py
examples/heat_pipe_in_cylindrical_geometry/2_postprocessing.py
tests/helpers.py
tests/test_capillarity.py
tests/test_cli.py
tests/test_h5.py
tests/test_input.py
tests/test_mesh_methods.py
tests/test_mesh_properties.py
tests/test_meshio.py
tests/test_meshmaker.py
tests/test_output.py
tests/test_react.py
tests/test_relative_permeability.py
tests/test_run.py
tests/test_table.py
tests/test_time_series.py
tests/test_tough.py
toughio/VERSION
toughio/__about__.py
toughio/__init__.py
toughio/_common.py
toughio/_exceptions.py
toughio/_helpers.py
toughio/_run.py
toughio/_cli/__init__.py
toughio/_cli/_co2tab.py
toughio/_cli/_export.py
toughio/_cli/_extract.py
toughio/_cli/_merge.py
toughio/_cli/_save2incon.py
toughio/_io/__init__.py
toughio/_io/_common.py
toughio/_io/h5/__init__.py
toughio/_io/h5/_write.py
toughio/_io/input/__init__.py
toughio/_io/input/_common.py
toughio/_io/input/_helpers.py
toughio/_io/input/json/__init__.py
toughio/_io/input/json/_json.py
toughio/_io/input/tough/__init__.py
toughio/_io/input/tough/_common.py
toughio/_io/input/tough/_helpers.py
toughio/_io/input/tough/_read.py
toughio/_io/input/tough/_write.py
toughio/_io/input/toughreact_chemical/__init__.py
toughio/_io/input/toughreact_chemical/_helpers.py
toughio/_io/input/toughreact_chemical/_read.py
toughio/_io/input/toughreact_chemical/_write.py
toughio/_io/input/toughreact_flow/__init__.py
toughio/_io/input/toughreact_flow/_toughreact_flow.py
toughio/_io/input/toughreact_solute/__init__.py
toughio/_io/input/toughreact_solute/_common.py
toughio-1.15.1.dist-info/LICENSE
toughio-1.15.1.dist-info/METADATA
toughio-1.15.1.dist-info/WHEEL
toughio-1.15.1.dist-info/entry_points.txt
toughio-1.15.1.dist-info/top_level.txt
toughio-1.15.1.dist-info/RECORD
