Metadata-Version: 2.1
Name: toughio
Version: 1.15.1
Summary: Pre- and post-processing Python library for TOUGH
Home-page: https://github.com/keurfonluu/toughio
Author: Keurfon Luu
License: BSD 3-Clause License
Project-URL: Code, https://github.com/keurfonluu/toughio
Project-URL: Issues, https://github.com/keurfonluu/toughio/issues
Platform: any
Classifier: License :: OSI Approved :: BSD License
Classifier: Operating System :: OS Independent
Classifier: Development Status :: 5 - Production/Stable
Classifier: Programming Language :: Python :: 3.7
Classifier: Programming Language :: Python :: 3.8
Classifier: Programming Language :: Python :: 3.9
Classifier: Programming Language :: Python :: 3.10
Classifier: Programming Language :: Python :: 3.11
Classifier: Programming Language :: Python :: 3.12
Classifier: Natural Language :: English
Classifier: Intended Audience :: Science/Research
Classifier: Topic :: Scientific/Engineering
Requires-Python: >=3.7
License-File: LICENSE
Requires-Dist: importlib_metadata
Requires-Dist: numpy>=1.13.0
Requires-Dist: meshio<6.0,>=5.2
Requires-Dist: psutil>=5.0
Provides-Extra: full
Requires-Dist: pyvista>=0.36; extra == "full"
Requires-Dist: netcdf4; extra == "full"
Requires-Dist: matplotlib; extra == "full"
Requires-Dist: h5py; extra == "full"
Requires-Dist: scipy>=0.9; extra == "full"
